AUTHORS.rst
CHANGELOG.rst
LICENSE
MANIFEST.in
README.rst
setup.py
janrain/__init__.py
janrain/middleware.py
janrain/models.py
janrain/retrieve_data.py
janrain/tests.py
janrain/urls.py
janrain/utils.py
janrain/widgets.py
janrain/migrations/0001_initial.py
janrain/migrations/0001_initial.pyc
janrain/migrations/0002_auto__add_field_janrainprofile_last_synced__add_field_janrainprofile_s.py
janrain/migrations/0002_auto__add_field_janrainprofile_last_synced__add_field_janrainprofile_s.pyc
janrain/migrations/__init__.py
janrain/migrations/__init__.pyc
jmbo_janrain.egg-info/PKG-INFO
jmbo_janrain.egg-info/SOURCES.txt
jmbo_janrain.egg-info/dependency_links.txt
jmbo_janrain.egg-info/not-zip-safe
jmbo_janrain.egg-info/requires.txt
jmbo_janrain.egg-info/top_level.txt